{"week":"2026-W25","date":"2026-06-18","weeks_archived":52,"count":20,"roster_hits":9,"roster_supported":106,"entries":[{"rank":1,"artist":"Green Velvet vs. MEDUZA & GENESI & ESSENTIA","title":"La La Land","url":"https://www.1001tracklists.com/track/h5bumxsf/green-velvet-meduza-genesi-essentia-la-la-land/index.html","roster":[{"name":"Green Velvet","slug":"green-velvet"},{"name":"Meduza","slug":"meduza"},{"name":"Genesi","slug":"genesi"}]},{"rank":2,"artist":"CamelPhat & Josh Gigante ft. Kuuda","title":"So Good","url":"https://www.1001tracklists.com/track/ujm3fjxp/camelphat-josh-gigante-so-good/index.html","roster":[{"name":"CamelPhat","slug":"camelphat"},{"name":"Josh Gigante","slug":"josh-gigante"}]},{"rank":3,"artist":"David Guetta & MARTEN HØRGER pres. Men Machine","title":"The Past, The Present, The Future","url":"https://www.1001tracklists.com/track/jmwct1t5/david-guetta-marten-horger-men-machine-the-past-the-present-the-future/index.html","roster":[]},{"rank":4,"artist":"KREAM & Korolova","title":"Annihilation","url":"https://www.1001tracklists.com/track/mucg5z5x/kream-korolova-annihilation/index.html","roster":[]},{"rank":5,"artist":"Vintage Culture & Volkoder","title":"Hands Up","url":"https://www.1001tracklists.com/track/f45b4lhp/vintage-culture-volkoder-hands-up/index.html","roster":[{"name":"Vintage Culture","slug":"vintage-culture"},{"name":"Volkoder","slug":"volkoder"}]},{"rank":6,"artist":"Cloonee & Prospa","title":"Free Your Mind","url":"https://www.1001tracklists.com/track/ffh0prbx/cloonee-prospa-free-your-mind/index.html","roster":[{"name":"Cloonee","slug":"cloonee"},{"name":"Prospa","slug":"prospa"}]},{"rank":7,"artist":"Prospa & Murda Beatz","title":"Baby","url":"https://www.1001tracklists.com/track/pl8kkjrp/prospa-murda-beatz-baby/index.html","roster":[{"name":"Prospa","slug":"prospa"}]},{"rank":8,"artist":"Alesso & JOA ft. Tyree Cooper","title":"Turn Up The Bass","url":"https://www.1001tracklists.com/track/4zfc08uf/alesso-joa-turn-up-the-bass/index.html","roster":[]},{"rank":9,"artist":"Armin van Buuren & Hannah Laing & Wippenberg","title":"U Got 2 Know","url":"https://www.1001tracklists.com/track/vdh3jr45/armin-van-buuren-hannah-laing-wippenberg-u-got-2-know/index.html","roster":[]},{"rank":null,"artist":"Charles D (USA) & Weska & Bexxie","title":"Can't Get Enough","url":"https://www.1001tracklists.com/track/pl7p6x0p/charles-d-usa-weska-bexxie-cant-get-enough/index.html","roster":[]},{"rank":11,"artist":"MEDUZA & RANI","title":"Silence","url":"https://www.1001tracklists.com/track/f4654nw5/meduza-rani-silence/index.html","roster":[{"name":"Meduza","slug":"meduza"}]},{"rank":null,"artist":"Miss Monique & Nicolas Taboada & FRANCO BA","title":"Ghosts","url":"https://www.1001tracklists.com/track/5l1hn7qx/miss-monique-nicolas-taboada-franco-ba-ghosts/index.html","roster":[]},{"rank":13,"artist":"HUGEL & Imael Angel & Ultra Naté","title":"Movin' To The Sun","url":"https://www.1001tracklists.com/track/duw3w1tf/hugel-imael-angel-ultra-nate-movin-to-the-sun/index.html","roster":[{"name":"Hugel","slug":"hugel"},{"name":"Ultra Nate","slug":"ultra-nate"}]},{"rank":14,"artist":"Max Styler & Greggio","title":"Oldskool Flavor","url":"https://www.1001tracklists.com/track/vz53bqff/max-styler-greggio-oldskool-flavor/index.html","roster":[{"name":"Max Styler","slug":"max-styler"}]},{"rank":null,"artist":"David Guetta & MARTEN HØRGER pres. Men Machine ft. Vitalic","title":"Engage","url":"https://www.1001tracklists.com/track/ujk7d8gp/david-guetta-marten-horger-men-machine-engage/index.html","roster":[]},{"rank":16,"artist":"Chris Avantgarde","title":"Rhythm Check","url":"https://www.1001tracklists.com/track/43h4plqf/chris-avantgarde-rhythm-check/index.html","roster":[]},{"rank":null,"artist":"JOSHWA","title":"Work Your Body","url":"https://www.1001tracklists.com/track/9xrt57g5/joshwa-work-your-body/index.html","roster":[]},{"rank":18,"artist":"David Forbes & Sue McLaren","title":"Satellite","url":"https://www.1001tracklists.com/track/cd9r86n5/david-forbes-sue-mclaren-satellite/index.html","roster":[]},{"rank":19,"artist":"Kryder","title":"Eivissa","url":"https://www.1001tracklists.com/track/85vttw05/kryder-eivissa/index.html","roster":[]},{"rank":null,"artist":"Joris Voorn & Roddy Lima & Taylr Renee","title":"Machine","url":"https://www.1001tracklists.com/track/jx7pcj8f/joris-voorn-roddy-lima-taylr-renee-machine/index.html","roster":[{"name":"Joris Voorn","slug":"joris-voorn"},{"name":"Roddy Lima","slug":"roddy-lima"}]}],"top_supported":[{"name":"Max Styler","slug":"max-styler","score":93,"weeks":23,"best":1,"now":true,"recent":true,"sets":4,"set_recent":true},{"name":"Vintage Culture","slug":"vintage-culture","score":92,"weeks":22,"best":1,"now":true,"recent":true,"sets":3,"set_recent":true},{"name":"Argy","slug":"argy","score":90,"weeks":21,"best":1,"now":false,"recent":true,"sets":0,"set_recent":false},{"name":"ARTBAT","slug":"artbat","score":89,"weeks":27,"best":1,"now":false,"recent":false,"sets":1,"set_recent":true},{"name":"Prospa","slug":"prospa","score":85,"weeks":19,"best":2,"now":true,"recent":true,"sets":8,"set_recent":true},{"name":"Meduza","slug":"meduza","score":85,"weeks":18,"best":1,"now":true,"recent":true,"sets":9,"set_recent":true},{"name":"Chris Lake","slug":"chris-lake","score":83,"weeks":18,"best":2,"now":false,"recent":true,"sets":1,"set_recent":true},{"name":"CamelPhat","slug":"camelphat","score":80,"weeks":16,"best":2,"now":true,"recent":true,"sets":6,"set_recent":true},{"name":"Tiga","slug":"tiga","score":80,"weeks":15,"best":1,"now":false,"recent":true,"sets":1,"set_recent":true},{"name":"Mau P","slug":"mau-p","score":79,"weeks":21,"best":1,"now":false,"recent":false,"sets":1,"set_recent":true},{"name":"Chris Lorenzo","slug":"chris-lorenzo","score":77,"weeks":15,"best":3,"now":false,"recent":true,"sets":1,"set_recent":true},{"name":"Genesi","slug":"genesi","score":75,"weeks":12,"best":1,"now":true,"recent":true,"sets":3,"set_recent":true},{"name":"Adam Beyer","slug":"adam-beyer","score":73,"weeks":12,"best":2,"now":false,"recent":true,"sets":1,"set_recent":true},{"name":"Green Velvet","slug":"green-velvet","score":73,"weeks":11,"best":1,"now":true,"recent":true,"sets":3,"set_recent":true},{"name":"Cloonee","slug":"cloonee","score":72,"weeks":11,"best":2,"now":true,"recent":true,"sets":6,"set_recent":true},{"name":"Mark Knight","slug":"mark-knight","score":67,"weeks":15,"best":2,"now":false,"recent":false,"sets":5,"set_recent":true},{"name":"Josh Gigante","slug":"josh-gigante","score":67,"weeks":8,"best":2,"now":true,"recent":true,"sets":3,"set_recent":true},{"name":"FISHER","slug":"fisher","score":66,"weeks":14,"best":2,"now":false,"recent":false,"sets":2,"set_recent":true},{"name":"Joris Voorn","slug":"joris-voorn","score":63,"weeks":10,"best":6,"now":false,"recent":true,"sets":1,"set_recent":true},{"name":"Yotto","slug":"yotto","score":62,"weeks":14,"best":1,"now":false,"recent":false,"sets":0,"set_recent":false},{"name":"ANOTR","slug":"anotr","score":62,"weeks":8,"best":2,"now":false,"recent":true,"sets":8,"set_recent":true},{"name":"Anyma","slug":"anyma","score":59,"weeks":9,"best":1,"now":false,"recent":false,"sets":3,"set_recent":true},{"name":"Layton Giordani","slug":"layton-giordani","score":59,"weeks":9,"best":1,"now":false,"recent":false,"sets":4,"set_recent":true},{"name":"Volkoder","slug":"volkoder","score":58,"weeks":5,"best":4,"now":true,"recent":true,"sets":2,"set_recent":true},{"name":"James Hype","slug":"james-hype","score":57,"weeks":12,"best":2,"now":false,"recent":false,"sets":2,"set_recent":true},{"name":"Reinier Zonneveld","slug":"reinier-zonneveld","score":56,"weeks":7,"best":1,"now":false,"recent":false,"sets":1,"set_recent":true},{"name":"Gordo","slug":"gordo","score":56,"weeks":7,"best":1,"now":false,"recent":false,"sets":0,"set_recent":false},{"name":"Dom Dolla","slug":"dom-dolla","score":53,"weeks":4,"best":6,"now":false,"recent":true,"sets":0,"set_recent":false},{"name":"Armand Van Helden","slug":"armand-van-helden","score":52,"weeks":6,"best":2,"now":false,"recent":false,"sets":2,"set_recent":true},{"name":"Hugel","slug":"hugel","score":51,"weeks":6,"best":9,"now":true,"recent":true,"sets":6,"set_recent":true},{"name":"Adriatique","slug":"adriatique","score":49,"weeks":9,"best":7,"now":false,"recent":false,"sets":2,"set_recent":true},{"name":"Fred again..","slug":"fred-again","score":49,"weeks":4,"best":2,"now":false,"recent":false,"sets":1,"set_recent":true},{"name":"Franky Rizardo","slug":"franky-rizardo","score":47,"weeks":5,"best":4,"now":false,"recent":false,"sets":1,"set_recent":true},{"name":"Ultra Nate","slug":"ultra-nate","score":46,"weeks":3,"best":9,"now":true,"recent":true,"sets":5,"set_recent":true},{"name":"SIDEPIECE","slug":"sidepiece","score":44,"weeks":6,"best":7,"now":false,"recent":false,"sets":0,"set_recent":false},{"name":"Jamback","slug":"jamback","score":42,"weeks":7,"best":6,"now":false,"recent":false,"sets":0,"set_recent":false},{"name":"John Summit","slug":"john-summit","score":40,"weeks":5,"best":5,"now":false,"recent":false,"sets":5,"set_recent":true},{"name":"Gorgon City","slug":"gorgon-city","score":39,"weeks":4,"best":5,"now":false,"recent":false,"sets":0,"set_recent":false},{"name":"Cristoph","slug":"cristoph","score":38,"weeks":4,"best":8,"now":false,"recent":false,"sets":2,"set_recent":true},{"name":"D.O.D","slug":"d-o-d","score":37,"weeks":7,"best":15,"now":false,"recent":true,"sets":0,"set_recent":false},{"name":"Dean Turnley","slug":"dean-turnley","score":37,"weeks":5,"best":13,"now":false,"recent":true,"sets":2,"set_recent":true},{"name":"Jitwam","slug":"jitwam","score":37,"weeks":3,"best":8,"now":false,"recent":false,"sets":0,"set_recent":false},{"name":"GUDFELLA","slug":"gudfella","score":37,"weeks":3,"best":8,"now":false,"recent":false,"sets":5,"set_recent":true},{"name":"Bob Sinclar","slug":"bob-sinclar","score":35,"weeks":0,"best":null,"now":false,"recent":false,"sets":5,"set_recent":true},{"name":"Disco Lines","slug":"disco-lines","score":35,"weeks":0,"best":null,"now":false,"recent":false,"sets":5,"set_recent":true},{"name":"BLOND:ISH","slug":"blond-ish","score":32,"weeks":5,"best":10,"now":false,"recent":false,"sets":1,"set_recent":true},{"name":"Agents Of Time","slug":"agents-of-time","score":32,"weeks":3,"best":11,"now":false,"recent":false,"sets":1,"set_recent":true},{"name":"Roddy Lima","slug":"roddy-lima","score":30,"weeks":3,"best":18,"now":false,"recent":true,"sets":1,"set_recent":true},{"name":"Sonny Fodera","slug":"sonny-fodera","score":28,"weeks":1,"best":15,"now":false,"recent":false,"sets":4,"set_recent":true},{"name":"Disclosure","slug":"disclosure","score":27,"weeks":3,"best":11,"now":false,"recent":false,"sets":0,"set_recent":false}]}